term_frequency/PdfReader.py
term_frequency/__init__.py
term_frequency/cli.py
term_frequency/config.py
term_frequency/db.py
term_frequency/extract.py
term_frequency/term_frequency.py
term_frequency/tf_idf.py
term_frequency/tfidf.py
Adsys_PDFReaderTool-0.0.1.dist-info/AUTHORS.rst
Adsys_PDFReaderTool-0.0.1.dist-info/LICENSE
Adsys_PDFReaderTool-0.0.1.dist-info/METADATA
Adsys_PDFReaderTool-0.0.1.dist-info/WHEEL
Adsys_PDFReaderTool-0.0.1.dist-info/entry_points.txt
Adsys_PDFReaderTool-0.0.1.dist-info/top_level.txt
Adsys_PDFReaderTool-0.0.1.dist-info/RECORD
